strengths/rdspacebase.py
strengths/rdengine.py
strengths/rdspace.py
strengths/plot.py
strengths/units.py
strengths/value_processing.py
strengths/engine_collection.py
strengths/rdscript.py
strengths/rdgridspace.py
strengths/constants.py
strengths/simulate.py
strengths/scipyrdengine.py
strengths/kineticsrdengine.py
strengths/__init__.py
strengths/rdoutput.py
strengths/rdgraphspace.py
strengths/text_array_rw.py
strengths/rdsystem.py
strengths/coarsegrain.py
strengths/typechecking.py
strengths/filepath.py
strengths/ode.py
strengths/sampler.py
strengths/rdnetwork.py
strengths/kinetics.py
strengths/librdengine.py
strengths/engines/strengths_engine/engine.pypy37-pp73-darwin.so
strengths/engines/strengths_engine/src/GillespieGraph.hpp
strengths/engines/strengths_engine/src/TauLeap3D.hpp
strengths/engines/strengths_engine/src/TauLeapGraph.hpp
strengths/engines/strengths_engine/src/Gillespie3D.hpp
strengths/engines/strengths_engine/src/SimulationAlgorithm3DBase.hpp
strengths/engines/strengths_engine/src/SimulationAlgorithmGraphBase.hpp
strengths/engines/strengths_engine/src/Euler3D.hpp
strengths/engines/strengths_engine/src/engine.cpp
strengths/engines/strengths_engine/src/EulerGraph.hpp
strengths-0.1.2.dist-info/RECORD
strengths-0.1.2.dist-info/LICENSE
strengths-0.1.2.dist-info/WHEEL
strengths-0.1.2.dist-info/top_level.txt
strengths-0.1.2.dist-info/METADATA
