Metadata-Version: 2.1
Name: strengths
Version: 0.1.2
Summary: A package for the modeling and simulation of reaction-diffusion systems.
Author: Thibault Fillion, Francesco Piazza
License-File: LICENSE
Requires-Dist: numpy
Requires-Dist: matplotlib
